genal/Geno.py
genal/MR.py
genal/MR_tools.py
genal/MRpresso.py
genal/__init__.py
genal/association.py
genal/clump.py
genal/colocalization.py
genal/constants.py
genal/extract_prs.py
genal/genes.py
genal/geno_tools.py
genal/lift.py
genal/plots.py
genal/proxy.py
genal/snp_query.py
genal/tools.py
genal_python-1.5.1.dist-info/licenses/LICENSE
genal_python-1.5.1.dist-info/WHEEL
genal_python-1.5.1.dist-info/METADATA
genal_python-1.5.1.dist-info/RECORD
