Metadata-Version: 2.4
Name: genal-python
Version: 1.5.1
Summary: A python toolkit for polygenic risk scoring and mendelian randomization.
Author-email: Cyprien Rivier <riviercyprien@gmail.com>
Requires-Python: >=3.8
Classifier: Programming Language :: Python :: 3
Classifier: License :: OSI Approved :: GNU General Public License v3 or later (GPLv3+)
Classifier: Operating System :: OS Independent
License-File: LICENSE
Requires-Dist: aiohttp>=3.7
Requires-Dist: nest_asyncio>=1.5
Requires-Dist: numpy>=1.17.3
Requires-Dist: pandas>=1.0
Requires-Dist: plotnine>=0.9
Requires-Dist: psutil>=5.0
Requires-Dist: requests>=2.0
Requires-Dist: pyliftover>=0.4
Requires-Dist: scikit_learn>=0.24
Requires-Dist: scipy>=1.7,<1.13
Requires-Dist: statsmodels>=0.13,<0.15
Requires-Dist: tqdm>=4.38
Requires-Dist: wget>=3.0
Requires-Dist: fastparquet>=0.4
Requires-Dist: pyarrow>=3.0
Requires-Dist: pytest>=7.0 ; extra == "test"
Requires-Dist: pytest-cov ; extra == "test"
Requires-Dist: pytest-xdist ; extra == "test"
Project-URL: Home, https://github.com/CypRiv/genal
Provides-Extra: test
